odoo/addons/shopfloor_gs1/README.rst
odoo/addons/shopfloor_gs1/__init__.py
odoo/addons/shopfloor_gs1/__manifest__.py
odoo/addons/shopfloor_gs1/config.py
odoo/addons/shopfloor_gs1/utils.py
odoo/addons/shopfloor_gs1/actions/__init__.py
odoo/addons/shopfloor_gs1/actions/search.py
odoo/addons/shopfloor_gs1/i18n/it.po
odoo/addons/shopfloor_gs1/i18n/shopfloor_gs1.pot
odoo/addons/shopfloor_gs1/readme/CONTRIBUTORS.md
odoo/addons/shopfloor_gs1/readme/DESCRIPTION.md
odoo/addons/shopfloor_gs1/readme/USAGE.md
odoo/addons/shopfloor_gs1/static/description/icon.png
odoo/addons/shopfloor_gs1/static/description/index.html
odoo/addons/shopfloor_gs1/tests/__init__.py
odoo/addons/shopfloor_gs1/tests/common.py
odoo/addons/shopfloor_gs1/tests/test_action_search.py
odoo/addons/shopfloor_gs1/tests/test_action_search_hri.py
odoo/addons/shopfloor_gs1/tests/test_scan_anything.py
odoo/addons/shopfloor_gs1/tests/test_utils.py
odoo_addon_shopfloor_gs1-18.0.1.0.0.4.dist-info/METADATA
odoo_addon_shopfloor_gs1-18.0.1.0.0.4.dist-info/WHEEL
odoo_addon_shopfloor_gs1-18.0.1.0.0.4.dist-info/top_level.txt
odoo_addon_shopfloor_gs1-18.0.1.0.0.4.dist-info/RECORD
